markov/__init__.py
markov/exceptions.py
markov/core/__init__.py
markov/core/algorithms.py
markov/core/base.py
markov/core/continuous.py
markov/core/discrete.py
markov/utils/__init__.py
markov/utils/io.py
markov/utils/math_utils.py
markov/utils/metrics.py
markov/utils/validation.py
python_markov-0.1.0.dist-info/METADATA
python_markov-0.1.0.dist-info/WHEEL
python_markov-0.1.0.dist-info/licenses/LICENSE
python_markov-0.1.0.dist-info/RECORD
